Metadata-Version: 2.1
Name: dsdpack
Version: 0.0.0
Summary: A package to describe structured data with tags and options
Home-page: UNKNOWN
Author: Takanori Kono
License: UNKNOWN
Platform: UNKNOWN
Requires-Python: >=3.7
